odoo/addons/document_page_procedure/README.rst
odoo/addons/document_page_procedure/__init__.py
odoo/addons/document_page_procedure/__manifest__.py
odoo/addons/document_page_procedure/data/document_page_procedure.xml
odoo/addons/document_page_procedure/demo/document_page_procedure.xml
odoo/addons/document_page_procedure/i18n/de.po
odoo/addons/document_page_procedure/i18n/document_page_procedure.pot
odoo/addons/document_page_procedure/i18n/es.po
odoo/addons/document_page_procedure/i18n/es_CO.po
odoo/addons/document_page_procedure/i18n/fr.po
odoo/addons/document_page_procedure/i18n/hr.po
odoo/addons/document_page_procedure/i18n/hr_HR.po
odoo/addons/document_page_procedure/i18n/hu.po
odoo/addons/document_page_procedure/i18n/it.po
odoo/addons/document_page_procedure/i18n/nb.po
odoo/addons/document_page_procedure/i18n/nl_NL.po
odoo/addons/document_page_procedure/i18n/pt.po
odoo/addons/document_page_procedure/i18n/pt_BR.po
odoo/addons/document_page_procedure/i18n/sl.po
odoo/addons/document_page_procedure/i18n/sv.po
odoo/addons/document_page_procedure/i18n/vi.po
odoo/addons/document_page_procedure/readme/CONFIGURE.rst
odoo/addons/document_page_procedure/readme/CONTRIBUTORS.rst
odoo/addons/document_page_procedure/readme/DESCRIPTION.rst
odoo/addons/document_page_procedure/static/description/icon.png
odoo/addons/document_page_procedure/static/description/index.html
odoo/addons/document_page_procedure/views/document_page_procedure.xml
odoo12_addon_document_page_procedure-12.0.1.0.0.99.dev6.dist-info/METADATA
odoo12_addon_document_page_procedure-12.0.1.0.0.99.dev6.dist-info/WHEEL
odoo12_addon_document_page_procedure-12.0.1.0.0.99.dev6.dist-info/top_level.txt
odoo12_addon_document_page_procedure-12.0.1.0.0.99.dev6.dist-info/RECORD
